epomatti_aksmrc_core/__init__.py
epomatti_aksmrc_core/keyvault.py
epomatti_aksmrc_core/mongo.py
epomatti_aksmrc_core/msal.py
epomatti_aksmrc_core/token_credential.py
epomatti_aksmrc_core/utils.py
epomatti_aksmrc_core/validators.py
epomatti_aksmrc_core-0.1.7.dist-info/WHEEL
epomatti_aksmrc_core-0.1.7.dist-info/METADATA
epomatti_aksmrc_core-0.1.7.dist-info/RECORD
