Metadata-Version: 2.1
Name: epomatti-aksmrc-core
Version: 0.1.7
Summary: Shared code for my multi region AKS cluster microservices.
Home-page: https://github.com/epomatti/azure-multiregion-aks-cluster
Author: Evandro Pomatti
Author-email: evandro.pomatti@gmail.com
Requires-Python: >=3.10,<4.0
Classifier: Programming Language :: Python :: 3
Classifier: Programming Language :: Python :: 3.10
Requires-Dist: Cerberus (>=1.3.4,<2.0.0)
Requires-Dist: Flask (>=2.1.2,<3.0.0)
Requires-Dist: azure-identity (>=1.10.0,<2.0.0)
Requires-Dist: azure-keyvault-secrets (>=4.4.0,<5.0.0)
Requires-Dist: pymongo (>=4.1.1,<5.0.0)
Project-URL: Repository, https://github.com/epomatti/azure-multiregion-aks-cluster
